rm_anime_bg/cli.py
rm_anime_bg-0.2.0.dist-info/LICENSE.txt
rm_anime_bg-0.2.0.dist-info/METADATA
rm_anime_bg-0.2.0.dist-info/WHEEL
rm_anime_bg-0.2.0.dist-info/entry_points.txt
rm_anime_bg-0.2.0.dist-info/RECORD
