Metadata-Version: 2.1
Name: rm-anime-bg
Version: 0.2.0
Summary: 
Home-page: https://github.com/shirayu/rm_anime_bg.git
License: Apache-2.0
Author: Yuta Hayashibe
Author-email: yuta@hayashibe.jp
Requires-Python: >=3.9,<3.11
Classifier: License :: OSI Approved :: Apache Software License
Classifier: Programming Language :: Python :: 3
Classifier: Programming Language :: Python :: 3.9
Classifier: Programming Language :: Python :: 3.10
Provides-Extra: cpu
Provides-Extra: gpu
Requires-Dist: huggingface-hub (>=0.14.1)
Requires-Dist: numpy (>=1.24.2)
Requires-Dist: onnxruntime (>=1.15.1,<2.0.0) ; extra == "cpu"
Requires-Dist: onnxruntime-gpu (>=1.15.1,<2.0.0) ; extra == "gpu"
Requires-Dist: opencv-python (>=4.7.0.72)
Requires-Dist: torch (>=2.0.1,<3.0.0)
Project-URL: Repository, https://github.com/shirayu/rm_anime_bg.git
